video_anonymize/__init__.py
video_anonymize/anon.py
video_anonymize-0.0.dev0.dist-info/LICENSE
video_anonymize-0.0.dev0.dist-info/METADATA
video_anonymize-0.0.dev0.dist-info/WHEEL
video_anonymize-0.0.dev0.dist-info/entry_points.txt
video_anonymize-0.0.dev0.dist-info/top_level.txt
video_anonymize-0.0.dev0.dist-info/RECORD
